redefine/__init__.py
redefine/__main__.py
redefine/_cmd.py
redefine/redefine_installer
redefine/version_info.txt
redefine-0.24.30.dist-info/LICENSE
redefine-0.24.30.dist-info/METADATA
redefine-0.24.30.dist-info/WHEEL
redefine-0.24.30.dist-info/entry_points.txt
redefine-0.24.30.dist-info/top_level.txt
redefine-0.24.30.dist-info/RECORD
