Metadata-Version: 2.1
Name: redefine
Version: 0.24.30
Summary: Redefine is the first AI based CI optimization platform that seamlessly integrates with your existing CI environment
Home-page: https://redefine.dev/
Author: Redefine Software Ltd.
Author-email: info@redefine.dev
Maintainer: None
Maintainer-email: None
Requires-Python: >=3.6,<4.0
License-File: LICENSE
